heuristicsearch/__init__.py
heuristicsearch/a_star_search.py
heuristicsearch/ao_star.py
heuristicsearch/graph.py
heuristicsearch-0.1.1.dist-info/LICENSE.txt
heuristicsearch-0.1.1.dist-info/METADATA
heuristicsearch-0.1.1.dist-info/WHEEL
heuristicsearch-0.1.1.dist-info/top_level.txt
heuristicsearch-0.1.1.dist-info/RECORD
